HTTP/1.1 200 OK
Date: Wed, 23 Sep 2009 16:49:03 GMT
Server: Apache/2.2.3 (Red Hat)
Vary: Accept-Encoding
Content-Length: 1255
Connection: close
Content-Type: text/xml

<?xml version="1.0"?>
<character>
  <name>
    <firstname></firstname>
    <nick>Anulla</nick>
    <lastname></lastname>
  </name>
  <basic_stats>
    <level>24</level>
    <breed>Solitus</breed>
    <gender>Female</gender>
    <faction>Neutral</faction>
    <profession>Bureaucrat</profession>
    <defender_rank>Amateur</defender_rank>
    <defender_rank_id>2</defender_rank_id>
  </basic_stats>
  <pictureurl>http://www.anarchy-online.com/character/photos/40652.jpg</pictureurl>
  <smallpictureurl>http://www.anarchy-online.com/character/smallphotos/40652.jpg</smallpictureurl>
  <organization_membership>
    <organization_name>Elite Operations</organization_name>
    <rank>Applicant</rank>
    <rank_id>6</rank_id>
  </organization_membership>
  <history>
    <entry date="2009-09-17" level="24" ailevel="2" faction="Neutral" guild="Elite Operations" rank="Applicant" />
    <entry date="2009-03-28" level="15" ailevel="2" faction="Neutral" guild="Elite Operations" rank="Applicant" />
    <entry date="2009-03-27" level="13" ailevel="1" faction="Neutral" guild="Elite Operations" rank="Applicant" />
  </history>
  <last_updated>2009/09/17 07:53:04 Universal</last_updated>
  <last_changed>2009/09/17 07:53:04 Universal</last_changed>
</character>
